selenium_chrome/__constants.py
selenium_chrome/__init__.py
selenium_chrome/__utils.py
selenium_chrome/chrome.py
selenium_chrome/chrome_addons/__init__.py
selenium_chrome/chrome_addons/addon_manager.py
selenium_chrome/chrome_addons/chrome_addon_install_settings.py
selenium_chrome/chrome_addons/foxy_proxy_addon_settings.py
selenium_chrome/chrome_addons/ublock_origin_addon_settings.py
selenium_chrome/chrome_addons/builtin_addon_install_settings/__init__.py
selenium_chrome/chrome_addons/builtin_addon_install_settings/builtin_addon_install_settings.py
selenium_chrome/chrome_addons/builtin_addon_install_settings/resources/foxy_proxy/background.html
selenium_chrome/chrome_addons/builtin_addon_install_settings/resources/foxy_proxy/manifest.json
selenium_chrome/chrome_addons/builtin_addon_install_settings/resources/foxy_proxy/options.html
selenium_chrome/chrome_addons/builtin_addon_install_settings/resources/foxy_proxy/pac-sandbox.html
selenium_chrome/chrome_addons/builtin_addon_install_settings/resources/foxy_proxy/popup.html
selenium_chrome/chrome_addons/builtin_addon_install_settings/resources/foxy_proxy/_locales/en/messages.json
selenium_chrome/chrome_addons/builtin_addon_install_settings/resources/foxy_proxy/images/16x16.png
selenium_chrome/chrome_addons/builtin_addon_install_settings/resources/foxy_proxy/images/16x16.svg
selenium_chrome/chrome_addons/builtin_addon_install_settings/resources/foxy_proxy/images/Flag-map_of_the_United_States.svg
selenium_chrome/chrome_addons/builtin_addon_install_settings/resources/foxy_proxy/images/Flag_of_the_United_Kingdom.svg
selenium_chrome/chrome_addons/builtin_addon_install_settings/resources/foxy_proxy/images/Flag_of_the_United_States.svg
selenium_chrome/chrome_addons/builtin_addon_install_settings/resources/foxy_proxy/images/Flag_of_the_United_States_(3-2_aspect_ratio).svg
selenium_chrome/chrome_addons/builtin_addon_install_settings/resources/foxy_proxy/images/blank.gif
selenium_chrome-0.0.29.dist-info/LICENSE
selenium_chrome-0.0.29.dist-info/METADATA
selenium_chrome-0.0.29.dist-info/WHEEL
selenium_chrome-0.0.29.dist-info/top_level.txt
selenium_chrome-0.0.29.dist-info/RECORD
